fd2py.py
fd2py-1.1.data/scripts/fd2py.py
fd2py-1.1.dist-info/METADATA
fd2py-1.1.dist-info/WHEEL
fd2py-1.1.dist-info/top_level.txt
fd2py-1.1.dist-info/RECORD
